table2json/__init__.py
table2json/bin/__init__.py
table2json/bin/main.py
table2json/core/__init__.py
table2json/core/base.py
table2json/core/exceptions.py
table2json/core/formatter.py
table2json/core/helpers.py
table2json/core/parser.py
table2json/core/utility.py
table2json/core/wrapper.py
table2json/management/__init__.py
table2json/management/base.py
table2json/management/commands/__init__.py
table2json/management/commands/csv.py
table2json/management/commands/excel.py
table2json/management/commands/mysql.py
table2json/management/commands/neo4j.py
table2json/management/commands/sqlite.py
table2json/utils/__init__.py
table2json/utils/getter.py
Table2JSON-2.0.1.dist-info/LICENSE
Table2JSON-2.0.1.dist-info/METADATA
Table2JSON-2.0.1.dist-info/WHEEL
Table2JSON-2.0.1.dist-info/entry_points.txt
Table2JSON-2.0.1.dist-info/top_level.txt
Table2JSON-2.0.1.dist-info/RECORD
