Metadata-Version: 2.1
Name: Table2JSON
Version: 2.0.1
Summary: Convert Tabular Data to JSON
Home-page: https://github.com/amoghmadan/Table2JSON
Author: Amogh Madan
Author-email: amoghmadaan@gmail.com
License: MIT
Project-URL: Documentation, https://github.com/amoghmadan/Table2JSON
Platform: any
Classifier: Development Status :: 5 - Production/Stable
Classifier: Environment :: Console
Classifier: Intended Audience :: Developers
Classifier: Intended Audience :: System Administrators
Classifier: License :: OSI Approved :: MIT License
Classifier: Natural Language :: English
Classifier: Operating System :: OS Independent
Classifier: Programming Language :: Python
Classifier: Programming Language :: Python :: 3
Classifier: Programming Language :: Python :: 3 :: Only
Classifier: Programming Language :: Python :: 3.7
Classifier: Programming Language :: Python :: 3.8
Classifier: Programming Language :: Python :: 3.9
Classifier: Programming Language :: Python :: 3.10
Classifier: Topic :: Utilities
Requires-Python: <3.11,>=3.7
Provides-Extra: all
Provides-Extra: excel
Provides-Extra: mysql
Provides-Extra: neo4j
License-File: LICENSE
